climate_assessment/__init__.py
climate_assessment/checks.py
climate_assessment/cli.py
climate_assessment/climate/__init__.py
climate_assessment/climate/ciceroscm.py
climate_assessment/climate/fair.py
climate_assessment/climate/magicc7.py
climate_assessment/climate/post_process.py
climate_assessment/climate/variable_definitions.csv
climate_assessment/climate/wg3.py
climate_assessment/harmonization/__init__.py
climate_assessment/harmonization/aneris_ar6.yaml
climate_assessment/harmonization/aneris_ar6_co2.yaml
climate_assessment/harmonization/aneris_sr15.yaml
climate_assessment/harmonization/aneris_sr15_co2.yaml
climate_assessment/harmonization/history_ar6.csv
climate_assessment/harmonization/history_sr15.csv
climate_assessment/harmonization/regions_ar6.csv
climate_assessment/harmonization_and_infilling.py
climate_assessment/infilling/__init__.py
climate_assessment/infilling/cmip6-ssps-workflow-emissions.csv
climate_assessment/postprocess.py
climate_assessment/testing.py
climate_assessment/utils.py
climate_assessment-0.1.6.dist-info/LICENSE
climate_assessment-0.1.6.dist-info/METADATA
climate_assessment-0.1.6.dist-info/WHEEL
climate_assessment-0.1.6.dist-info/RECORD
