Metadata-Version: 2.3
Name: climate-assessment
Version: 0.1.6
Summary: Climate assessment of long-term emissions pathways: IPCC AR6 WGIII version
License: MIT
Keywords: climate,integrated assessment,emissions,temperature,IPCC
Author: Jarmo S. Kikstra
Author-email: kikstra@iiasa.ac.at
Requires-Python: >=3.11,<3.14
Classifier: Development Status :: 3 - Alpha
Classifier: Intended Audience :: Science/Research
Classifier: License :: OSI Approved :: MIT License
Classifier: Programming Language :: Python
Classifier: Programming Language :: Python :: 3
Classifier: Programming Language :: Python :: 3.11
Classifier: Topic :: Scientific/Engineering :: Atmospheric Science
Classifier: Operating System :: OS Independent
Classifier: Intended Audience :: Science/Research
Requires-Dist: aneris_iamc (==0.3.1)
Requires-Dist: fair (==1.6.2)
Requires-Dist: ixmp4 (>=0.9.10)
Requires-Dist: joblib (>=1.3.2,<2.0.0)
Requires-Dist: openscm-runner (==0.12.1)
Requires-Dist: pandas (>=2.2.2,<3.0.0)
Requires-Dist: pooch (>=1.8.0,<2.0.0)
Requires-Dist: pyam-iamc (>=2.2.2)
Requires-Dist: pymagicc (==2.1.5)
Requires-Dist: scmdata (>=0.18.0,<0.19.0)
Requires-Dist: setuptools (>=80.9.0,<81.0.0)
Requires-Dist: silicone (==1.3.0)
